driverscripts/__init__.py
driverscripts/driver_jacobian_product.py
driverscripts/driver_root_multivariate.py
driverscripts/driver_root_univariate.py
genericdiff/__init__.py
genericdiff/elemental_functions.py
genericdiff/generic_diff.py
genericdiff/vector_jacobian.py
rnavelocity/__init__.py
rnavelocity/example.py
rnavelocity/functions.py
rnavelocity/generate_minimum_spanning_tree.py
rnavelocity/initialization.py
rnavelocity/optimize_parameters.py
rnavelocity/rna_velocity.py
rnavelocity/time_sort.py
test/__init__.py
test/test_elemental_functions.py
test/test_generic_diff.py
test/test_generic_diff_comparison.py
test/test_vector_jacobian.py
rnavelocity_genericdiff-0.1.0.dist-info/LICENSE
rnavelocity_genericdiff-0.1.0.dist-info/METADATA
rnavelocity_genericdiff-0.1.0.dist-info/WHEEL
rnavelocity_genericdiff-0.1.0.dist-info/top_level.txt
rnavelocity_genericdiff-0.1.0.dist-info/RECORD
