Metadata-Version: 2.1
Name: rnavelocity-genericdiff
Version: 0.1.0
Summary: Package for RNA velocity, cell ordering and automatic differentiation
Home-page: https://github.com/Topcoder-Kitty-ML/cs207-FinalProject
Author: Top Coder Kitty ML
Author-email: mark.y.lock@gmail.com
License: UNKNOWN
Platform: UNKNOWN
Classifier: Programming Language :: Python :: 3
Classifier: License :: OSI Approved :: MIT License
Classifier: Operating System :: OS Independent
Requires-Python: >=3.6
Requires-Dist: numpy
Requires-Dist: pytest
Requires-Dist: matplotlib
